foctopus/__init__.py
foctopus/foctopus.py
foctopus-1.2.dist-info/METADATA
foctopus-1.2.dist-info/WHEEL
foctopus-1.2.dist-info/top_level.txt
foctopus-1.2.dist-info/RECORD
